sanic_mail/__init__.py
sanic_mail/exceptions.py
sanic_mail/utils.py
sanic_mail-0.0.3.dist-info/LICENSE
sanic_mail-0.0.3.dist-info/METADATA
sanic_mail-0.0.3.dist-info/WHEEL
sanic_mail-0.0.3.dist-info/top_level.txt
sanic_mail-0.0.3.dist-info/RECORD
