Metadata-Version: 2.1
Name: sanic-mail
Version: 0.0.3
Summary: async email sender for sanic
Home-page: https://github.com/Python-Tools/sanic-mail
Author: hsz
Author-email: hsz1273327@gmail.com
License: MIT License
Keywords: email,sanic
Classifier: License :: OSI Approved :: MIT License
Classifier: Programming Language :: Python :: 3.7
Classifier: Programming Language :: Python :: 3.8
Classifier: Programming Language :: Python :: 3.9
Classifier: Programming Language :: Python :: 3.10
License-File: LICENSE
Requires-Dist: sanic (>22.12.0)
Requires-Dist: aiosmtplib (>2.0.0)
